shipyard_sftp/__init__.py
shipyard_sftp/cli/__init__.py
shipyard_sftp/cli/authtest.py
shipyard_sftp/cli/delete_file.py
shipyard_sftp/cli/download_file.py
shipyard_sftp/cli/move_file.py
shipyard_sftp/cli/upload_file.py
shipyard_sftp/exceptions.py
shipyard_sftp/sftp.py
shipyard_sftp/utils.py
shipyard_sftp-0.3.3.dist-info/METADATA
shipyard_sftp-0.3.3.dist-info/WHEEL
shipyard_sftp-0.3.3.dist-info/RECORD
