Metadata-Version: 2.1
Name: shipyard-sftp
Version: 0.3.3
Summary: A local client for connecting and working with SFTP servers
License: Apache 2.0
Author: wrp801
Author-email: wespoulsen@gmail.com
Requires-Python: >=3.9,<4.0
Classifier: License :: Other/Proprietary License
Classifier: Programming Language :: Python :: 3
Classifier: Programming Language :: Python :: 3.9
Classifier: Programming Language :: Python :: 3.10
Classifier: Programming Language :: Python :: 3.11
Requires-Dist: paramiko (>=3.4.0,<4.0.0)
Requires-Dist: shipyard-bp-utils (>=1.2.0,<2.0.0)
Requires-Dist: shipyard-templates (>=0.8.0,<0.9.0)
